emrflow/__init__.py
emrflow/deployment/__init__.py
emrflow/deployment/emr.py
emrflow/deployment/emr_sls.py
emrflow/emr_serverless.py
emrflow/main.py
emrflow/package/__init__.py
emrflow/package/build_package.py
emrflow/package/create_env.py
emrflow/package/project_dependency_src.py
emrflow/utils/__init__.py
emrflow-1.4.1.dist-info/LICENSE
emrflow-1.4.1.dist-info/METADATA
emrflow-1.4.1.dist-info/WHEEL
emrflow-1.4.1.dist-info/entry_points.txt
emrflow-1.4.1.dist-info/RECORD
