Metadata-Version: 2.1
Name: EMRFlow
Version: 1.4.1
Summary: Run/Monitor your PySpark Jobs in Amazon EMR
Author: Utkarsh Vashisth
Author-email: utkarsh.vashisth@sanofi.com
Requires-Python: >=3.8,<4.0
Classifier: Programming Language :: Python :: 3
Classifier: Programming Language :: Python :: 3.8
Classifier: Programming Language :: Python :: 3.9
Classifier: Programming Language :: Python :: 3.10
Classifier: Programming Language :: Python :: 3.11
Classifier: Programming Language :: Python :: 3.12
Requires-Dist: boto3 (>=1.25.4)
Requires-Dist: typer[all] (>=0.12.0,<0.13.0)
